ywdblogmath2/__init__.py
ywdblogmath2/add.py
ywdblogmath2/division.py
ywdblogmath2/multiply.py
ywdblogmath2/subtract.py
ywdblogmath2/adv/__init__.py
ywdblogmath2/adv/sqrt.py
ywdblogmath2-0.2.dist-info/DESCRIPTION.rst
ywdblogmath2-0.2.dist-info/METADATA
ywdblogmath2-0.2.dist-info/RECORD
ywdblogmath2-0.2.dist-info/WHEEL
ywdblogmath2-0.2.dist-info/metadata.json
ywdblogmath2-0.2.dist-info/top_level.txt
